{"title":"Brujeria - Brujerizmo","uid":4591723,"size":42899456,"categoryP":"audio","categoryS":"music","magnet":"?xt=urn:btih:024d03e42f9441775f5c2c9e526ec29be6eefa57&amp;dn=Brujeria+-+Brujerizmo&amp;tr=udp%3A%2F%2Ftracker.openbittorrent.com%3A80&amp;tr=udp%3A%2F%2Fopen.demonii.com%3A1337&amp;tr=udp%3A%2F%2Ftracker.coppersurfer.tk%3A6969&amp;tr=udp%3A%2F%2Fexodus.desync.com%3A6969","seeders":1,"leechers":0,"uploader":"UberMetaller","files":13,"time":1229819923,"description":"Brujeria - Brujerizmo album. All tracks 160kbps.\n\nTrack listing:\n\n01 - Brujerizmo\n02 - Vayan Sin Miedo\n03 - La Traicion\n04 - Pititis Te Invoco\n05 - Laboratorio Cristalitos\n06 - Division Del Norte\n07 - Marcha De Odio\n08 - Anti - Castro\n09 - Cuiden A Los Ninos\n10 - El Bajon\n11 - Mecosario\n12 - El Desmadre\n13 - Sida De La Mente","torrent":{"xt":"urn:btih:024d03e42f9441775f5c2c9e526ec29be6eefa57","amp;dn":"Brujeria+-+Brujerizmo","amp;tr":["udp%3A%2F%2Ftracker.openbittorrent.com%3A80","udp%3A%2F%2Fopen.demonii.com%3A1337","udp%3A%2F%2Ftracker.coppersurfer.tk%3A6969","udp%3A%2F%2Fexodus.desync.com%3A6969"],"infoHash":"024d03e42f9441775f5c2c9e526ec29be6eefa57","infoHashBuffer":{"type":"Buffer","data":[2,77,3,228,47,148,65,119,95,92,44,158,82,110,194,155,230,238,250,87]},"announce":[],"urlList":[]}}