{"title":"Saturday.the.14th.1981.DVDRip.x264-EBX","uid":9898086,"size":745987956,"categoryP":"video","categoryS":"movies","magnet":"?xt=urn:btih:1a2c4c5b816639588b6cb68cc339f8f2fbb9cecc&amp;dn=Saturday.the.14th.1981.DVDRip.x264-EBX&amp;tr=udp%3A%2F%2Ftracker.openbittorrent.com%3A80&amp;tr=udp%3A%2F%2Fopen.demonii.com%3A1337&amp;tr=udp%3A%2F%2Ftracker.coppersurfer.tk%3A6969&amp;tr=udp%3A%2F%2Fexodus.desync.com%3A6969","seeders":1,"leechers":2,"uploader":"harks88","files":3,"time":1396739156,"description":"A Family moves into a house inhabited by scary creatures and a number of close calls ensue.\n\nSize: 734840853 bytes (700.80 MiB), duration: 01:16:45, avg.bitrate: 1277 kb/s\nAudio: aac, 48000 Hz, stereo (eng)\nVideo: h264, yuv420p, 710x480, 23.97 fps(r) =&gt; 631x480 (eng)\n\n-------------------------------------------------------------------------------------\n\nScreens:\n &lt;a href=&quot;\nhttp://www.thumbnailus.com/viewer.php?file=69398221497570597216.jpg&quot; rel=&quot;nofollow&quot; target=&quot;_NEW&quot;&gt;\nhttp://www.thumbnailus.com/viewer.php?file=69398221497570597216.jpg&lt;/a&gt;\n &lt;a href=&quot;\nhttp://www.thumbnailus.com/viewer.php?file=92401002604811651839.jpg&quot; rel=&quot;nofollow&quot; target=&quot;_NEW&quot;&gt;\nhttp://www.thumbnailus.com/viewer.php?file=92401002604811651839.jpg&lt;/a&gt;\n &lt;a href=&quot;\nhttp://www.thumbnailus.com/viewer.php?file=74099389066002429349.jpg&quot; rel=&quot;nofollow&quot; target=&quot;_NEW&quot;&gt;\nhttp://www.thumbnailus.com/viewer.php?file=74099389066002429349.jpg&lt;/a&gt;\n &lt;a href=&quot;\nhttp://www.thumbnailus.com/viewer.php?file=66300671816904906618.jpg&quot; rel=&quot;nofollow&quot; target=&quot;_NEW&quot;&gt;\nhttp://www.thumbnailus.com/viewer.php?file=66300671816904906618.jpg&lt;/a&gt;","torrent":{"xt":"urn:btih:1a2c4c5b816639588b6cb68cc339f8f2fbb9cecc","amp;dn":"Saturday.the.14th.1981.DVDRip.x264-EBX","amp;tr":["udp%3A%2F%2Ftracker.openbittorrent.com%3A80","udp%3A%2F%2Fopen.demonii.com%3A1337","udp%3A%2F%2Ftracker.coppersurfer.tk%3A6969","udp%3A%2F%2Fexodus.desync.com%3A6969"],"infoHash":"1a2c4c5b816639588b6cb68cc339f8f2fbb9cecc","infoHashBuffer":{"type":"Buffer","data":[26,44,76,91,129,102,57,88,139,108,182,140,195,57,248,242,251,185,206,204]},"announce":[],"urlList":[]}}