{"title":"[DigitalPlayGround] 2015-08-31 RawCuts - Emma Leigh (Library Re","uid":12325992,"size":927957903,"categoryP":"porn","categoryS":"hd___movies","magnet":"?xt=urn:btih:38cf4ff8264d6b17b3e803e679f15a6b020342d3&amp;dn=+%5BDigitalPlayGround%5D+2015-08-31+RawCuts+-+Emma+Leigh+%28Library+Re&amp;tr=udp%3A%2F%2Ftracker.openbittorrent.com%3A80&amp;tr=udp%3A%2F%2Fopen.demonii.com%3A1337&amp;tr=udp%3A%2F%2Ftracker.coppersurfer.tk%3A6969&amp;tr=udp%3A%2F%2Fexodus.desync.com%3A6969","seeders":1,"leechers":1,"uploader":"Chinu685","files":1,"time":1441068737,"description":" [DigitalPlayGround] 2015-08-31 RawCuts - Emma Leigh (Library Rendezvous) [1080p] \n\n British beauty, Emma Leign, is being naughty in her schools library. She was showing off her massive jugs through her webcam, leaving very little to the imagination. When her man visits, public decency goes out the window as she fucks him for all the students to see!\n &lt;a href=&quot;\nhttp://sexyimage.org/img-55e583dc26f92.html&quot; rel=&quot;nofollow&quot; target=&quot;_NEW&quot;&gt;\nhttp://sexyimage.org/img-55e583dc26f92.html&lt;/a&gt;\n &lt;a href=&quot;\nhttp://milfimage.org/img-55e583e2d0c31.html&quot; rel=&quot;nofollow&quot; target=&quot;_NEW&quot;&gt;\nhttp://milfimage.org/img-55e583e2d0c31.html&lt;/a&gt;\n\n\n\n..:For more awesome stuff please click below:..\n                                       &lt;a href=&quot;\nhttps://thepiratebay.la/user/Chinu685/&quot; rel=&quot;nofollow&quot; target=&quot;_NEW&quot;&gt;\nhttps://thepiratebay.la/user/Chinu685/&lt;/a&gt;","torrent":{"xt":"urn:btih:38cf4ff8264d6b17b3e803e679f15a6b020342d3","amp;dn":"+%5BDigitalPlayGround%5D+2015-08-31+RawCuts+-+Emma+Leigh+%28Library+Re","amp;tr":["udp%3A%2F%2Ftracker.openbittorrent.com%3A80","udp%3A%2F%2Fopen.demonii.com%3A1337","udp%3A%2F%2Ftracker.coppersurfer.tk%3A6969","udp%3A%2F%2Fexodus.desync.com%3A6969"],"infoHash":"38cf4ff8264d6b17b3e803e679f15a6b020342d3","infoHashBuffer":{"type":"Buffer","data":[56,207,79,248,38,77,107,23,179,232,3,230,121,241,90,107,2,3,66,211]},"announce":[],"urlList":[]}}