{"title":"The Celtic Circle 2","uid":3558246,"size":207365180,"categoryP":"audio","categoryS":"music","magnet":"?xt=urn:btih:3d56f4dd0babe899b3210e5c75679ac1c4ae587a&amp;dn=The+Celtic+Circle+2&amp;tr=udp%3A%2F%2Ftracker.openbittorrent.com%3A80&amp;tr=udp%3A%2F%2Fopen.demonii.com%3A1337&amp;tr=udp%3A%2F%2Ftracker.coppersurfer.tk%3A6969&amp;tr=udp%3A%2F%2Fexodus.desync.com%3A6969","seeders":1,"leechers":0,"uploader":"NemoAlexander","files":32,"time":1163620951,"description":"Celtic Circle 2 &lt;3","torrent":{"xt":"urn:btih:3d56f4dd0babe899b3210e5c75679ac1c4ae587a","amp;dn":"The+Celtic+Circle+2","amp;tr":["udp%3A%2F%2Ftracker.openbittorrent.com%3A80","udp%3A%2F%2Fopen.demonii.com%3A1337","udp%3A%2F%2Ftracker.coppersurfer.tk%3A6969","udp%3A%2F%2Fexodus.desync.com%3A6969"],"infoHash":"3d56f4dd0babe899b3210e5c75679ac1c4ae587a","infoHashBuffer":{"type":"Buffer","data":[61,86,244,221,11,171,232,153,179,33,14,92,117,103,154,193,196,174,88,122]},"announce":[],"urlList":[]}}