{"title":"Croczilla.2012.720p.DUBBED.BluRay.x264-PFa","uid":9420391,"size":4727002949,"categoryP":"video","categoryS":"hd___movies","magnet":"?xt=urn:btih:3d85b105ea341a954878ff78aa61e4d137e83aed&amp;dn=Croczilla.2012.720p.DUBBED.BluRay.x264-PFa&amp;tr=udp%3A%2F%2Ftracker.openbittorrent.com%3A80&amp;tr=udp%3A%2F%2Fopen.demonii.com%3A1337&amp;tr=udp%3A%2F%2Ftracker.coppersurfer.tk%3A6969&amp;tr=udp%3A%2F%2Fexodus.desync.com%3A6969","seeders":1,"leechers":0,"uploader":"Drarbg","files":5,"time":1388574510,"description":"Croczilla.2012.720p.DUBBED.BluRay.x264-PFa\n-----------------------------------------\nScreens : &lt;a href=&quot;\nhttp://imagecurl.org/viewer.php?file=31176744576872590567.jpg&quot; rel=&quot;nofollow&quot; target=&quot;_NEW&quot;&gt;\nhttp://imagecurl.org/viewer.php?file=31176744576872590567.jpg&lt;/a&gt;\n\n","torrent":{"xt":"urn:btih:3d85b105ea341a954878ff78aa61e4d137e83aed","amp;dn":"Croczilla.2012.720p.DUBBED.BluRay.x264-PFa","amp;tr":["udp%3A%2F%2Ftracker.openbittorrent.com%3A80","udp%3A%2F%2Fopen.demonii.com%3A1337","udp%3A%2F%2Ftracker.coppersurfer.tk%3A6969","udp%3A%2F%2Fexodus.desync.com%3A6969"],"infoHash":"3d85b105ea341a954878ff78aa61e4d137e83aed","infoHashBuffer":{"type":"Buffer","data":[61,133,177,5,234,52,26,149,72,120,255,120,170,97,228,209,55,232,58,237]},"announce":[],"urlList":[]}}