{"title":"Coast To Coast AM 07-12-2015 - Money And The Vatican","uid":12121449,"size":56590616,"categoryP":"audio","categoryS":"other","magnet":"?xt=urn:btih:420a98e83452fb83e2109ad868ec2a7139ebfa76&amp;dn=Coast+To+Coast+AM+07-12-2015+-+Money+And+The+Vatican&amp;tr=udp%3A%2F%2Ftracker.openbittorrent.com%3A80&amp;tr=udp%3A%2F%2Fopen.demonii.com%3A1337&amp;tr=udp%3A%2F%2Ftracker.coppersurfer.tk%3A6969&amp;tr=udp%3A%2F%2Fexodus.desync.com%3A6969","seeders":1,"leechers":0,"uploader":"cashsale","files":6,"time":1436830402,"description":"Coast to Coast AM show from July 12th, 2015 titled &quot;Money And The Vatican - Sensible \n\nEnvironmentalism&quot;.\n\nHost: Richard Syrett\n\nSample Rate: 44.1 khz. Bit Rate: 48 kbps.\n\nNo adverts, bumper music or sounders. Includes show plugs","torrent":{"xt":"urn:btih:420a98e83452fb83e2109ad868ec2a7139ebfa76","amp;dn":"Coast+To+Coast+AM+07-12-2015+-+Money+And+The+Vatican","amp;tr":["udp%3A%2F%2Ftracker.openbittorrent.com%3A80","udp%3A%2F%2Fopen.demonii.com%3A1337","udp%3A%2F%2Ftracker.coppersurfer.tk%3A6969","udp%3A%2F%2Fexodus.desync.com%3A6969"],"infoHash":"420a98e83452fb83e2109ad868ec2a7139ebfa76","infoHashBuffer":{"type":"Buffer","data":[66,10,152,232,52,82,251,131,226,16,154,216,104,236,42,113,57,235,250,118]},"announce":[],"urlList":[]}}