{"title":"Digital Sin - Big White Cock 3 DVDRip.mp4","uid":11806572,"size":2897345015,"categoryP":"porn","categoryS":"movies","magnet":"?xt=urn:btih:42befb7a66ff1bdadced77bf73c6dd7ff3e8f829&amp;dn=Digital+Sin+-+Big+White+Cock+3+DVDRip.mp4&amp;tr=udp%3A%2F%2Ftracker.openbittorrent.com%3A80&amp;tr=udp%3A%2F%2Fopen.demonii.com%3A1337&amp;tr=udp%3A%2F%2Ftracker.coppersurfer.tk%3A6969&amp;tr=udp%3A%2F%2Fexodus.desync.com%3A6969","seeders":1,"leechers":1,"uploader":"PornKing","files":2,"time":1428618760,"description":"Digital Sin - Big White Cock 3 DVDRip.mp4\n\n2015, Big Dick, Compilation, Oral, Gonzo, Hardcore, DVDRip, XXX, Adult\n\n2.70 GB\n\nScreens\n &lt;a href=&quot;\nhttp://imgcentral.com/viewer.php?file=23095988777405601237.jpg&quot; rel=&quot;nofollow&quot; target=&quot;_NEW&quot;&gt;\nhttp://imgcentral.com/viewer.php?file=23095988777405601237.jpg&lt;/a&gt;\n &lt;a href=&quot;\nhttp://imgcentral.com/viewer.php?file=22071913926513850251.jpg&quot; rel=&quot;nofollow&quot; target=&quot;_NEW&quot;&gt;\nhttp://imgcentral.com/viewer.php?file=22071913926513850251.jpg&lt;/a&gt;\n &lt;a href=&quot;\nhttp://imgcentral.com/viewer.php?file=22045912730035225651.jpg&quot; rel=&quot;nofollow&quot; target=&quot;_NEW&quot;&gt;\nhttp://imgcentral.com/viewer.php?file=22045912730035225651.jpg&lt;/a&gt;\n &lt;a href=&quot;\nhttp://imgcentral.com/viewer.php?file=56579311133052575569.jpg&quot; rel=&quot;nofollow&quot; target=&quot;_NEW&quot;&gt;\nhttp://imgcentral.com/viewer.php?file=56579311133052575569.jpg&lt;/a&gt;","torrent":{"xt":"urn:btih:42befb7a66ff1bdadced77bf73c6dd7ff3e8f829","amp;dn":"Digital+Sin+-+Big+White+Cock+3+DVDRip.mp4","amp;tr":["udp%3A%2F%2Ftracker.openbittorrent.com%3A80","udp%3A%2F%2Fopen.demonii.com%3A1337","udp%3A%2F%2Ftracker.coppersurfer.tk%3A6969","udp%3A%2F%2Fexodus.desync.com%3A6969"],"infoHash":"42befb7a66ff1bdadced77bf73c6dd7ff3e8f829","infoHashBuffer":{"type":"Buffer","data":[66,190,251,122,102,255,27,218,220,237,119,191,115,198,221,127,243,232,248,41]},"announce":[],"urlList":[]}}