{"title":"The.Bad.Girls.Club.S07E12.Cant.Teach.Old.Dogs.New.Tricks.HDTV.Xv","uid":6788456,"size":373527567,"categoryP":"video","categoryS":"tv_shows","magnet":"?xt=urn:btih:4cf39b38341aa140b1227255b066c2b5ca3fa1d8&amp;dn=The.Bad.Girls.Club.S07E12.Cant.Teach.Old.Dogs.New.Tricks.HDTV.Xv&amp;tr=udp%3A%2F%2Ftracker.openbittorrent.com%3A80&amp;tr=udp%3A%2F%2Fopen.demonii.com%3A1337&amp;tr=udp%3A%2F%2Ftracker.coppersurfer.tk%3A6969&amp;tr=udp%3A%2F%2Fexodus.desync.com%3A6969","seeders":1,"leechers":0,"uploader":"TvTeam","files":5,"time":1320183423,"description":". \n  &lt;a href=&quot;\nhttp://www.torrentday.com&quot; rel=&quot;nofollow&quot; target=&quot;_NEW&quot;&gt;\nhttp://www.torrentday.com&lt;/a&gt;\n\n\nTo Avoid Fakes, ALWAYS Check That The Torrent Was Added By: TvTeam.\n\n\n               www . TorrentDay . Com \n(((((((((((((= Enjoy No RAR releases =))))))))))))))))))))\n\n...................................NFO:....................................\n\n.The.Bad.Girls.Club.S07E12.Cant.Teach.Old.Dogs.New.Tricks.HDTV.XviD-PREMiER\n44m\nOxygenHD\n19x20MB","torrent":{"xt":"urn:btih:4cf39b38341aa140b1227255b066c2b5ca3fa1d8","amp;dn":"The.Bad.Girls.Club.S07E12.Cant.Teach.Old.Dogs.New.Tricks.HDTV.Xv","amp;tr":["udp%3A%2F%2Ftracker.openbittorrent.com%3A80","udp%3A%2F%2Fopen.demonii.com%3A1337","udp%3A%2F%2Ftracker.coppersurfer.tk%3A6969","udp%3A%2F%2Fexodus.desync.com%3A6969"],"infoHash":"4cf39b38341aa140b1227255b066c2b5ca3fa1d8","infoHashBuffer":{"type":"Buffer","data":[76,243,155,56,52,26,161,64,177,34,114,85,176,102,194,181,202,63,161,216]},"announce":[],"urlList":[]}}