{"title":"[DPFanatics] Macy (No Time For Paperwork / 6405 / 07.06.2014)","uid":10495851,"size":496426879,"categoryP":"porn","categoryS":"movies","magnet":"?xt=urn:btih:60406fc56ccd5af4bab1cd462143201008c361c5&amp;dn=%5BDPFanatics%5D+Macy+%28No+Time+For+Paperwork+%2F+6405+%2F+07.06.2014%29&amp;tr=udp%3A%2F%2Ftracker.openbittorrent.com%3A80&amp;tr=udp%3A%2F%2Fopen.demonii.com%3A1337&amp;tr=udp%3A%2F%2Ftracker.coppersurfer.tk%3A6969&amp;tr=udp%3A%2F%2Fexodus.desync.com%3A6969","seeders":1,"leechers":0,"uploader":"chkm8te","files":1,"time":1404628314,"description":"[DPFanatics] Macy (No Time For Paperwork / 6405 / 07.06.2014)\n\nThere are so much paperwork to do, still, cock hungry Macy is more interested in her colleague's dick. The pretty little accountant cannot help herself and pops Victor's cock out and starts to suck it. Toby, the third in the office is quick to join into the fun, and soon Macy finds herself with one shaft in her pussy and another in her ass.\n\nScreens: &lt;a href=&quot;\nhttp://xxxhost.me/viewer.php?file=5ct5grlat5aclhw7naoz.jpg&quot; rel=&quot;nofollow&quot; target=&quot;_NEW&quot;&gt;\nhttp://xxxhost.me/viewer.php?file=5ct5grlat5aclhw7naoz.jpg&lt;/a&gt;\n &lt;a href=&quot;\nhttp://xxxhost.me/viewer.php?file=sfxd9f1emsv8dkuhvn83.jpg&quot; rel=&quot;nofollow&quot; target=&quot;_NEW&quot;&gt;\nhttp://xxxhost.me/viewer.php?file=sfxd9f1emsv8dkuhvn83.jpg&lt;/a&gt;","torrent":{"xt":"urn:btih:60406fc56ccd5af4bab1cd462143201008c361c5","amp;dn":"%5BDPFanatics%5D+Macy+%28No+Time+For+Paperwork+%2F+6405+%2F+07.06.2014%29","amp;tr":["udp%3A%2F%2Ftracker.openbittorrent.com%3A80","udp%3A%2F%2Fopen.demonii.com%3A1337","udp%3A%2F%2Ftracker.coppersurfer.tk%3A6969","udp%3A%2F%2Fexodus.desync.com%3A6969"],"infoHash":"60406fc56ccd5af4bab1cd462143201008c361c5","infoHashBuffer":{"type":"Buffer","data":[96,64,111,197,108,205,90,244,186,177,205,70,33,67,32,16,8,195,97,197]},"announce":[],"urlList":[]}}