{"title":"8.Out.Of.10.Cats.S18E08.720p.HDTV.x264-TLA","uid":11563883,"size":783491095,"categoryP":"video","categoryS":"hd___tv_shows","magnet":"?xt=urn:btih:69a9695da3e31e8184ee908cde5a91c09e7701d6&amp;dn=8.Out.Of.10.Cats.S18E08.720p.HDTV.x264-TLA&amp;tr=udp%3A%2F%2Ftracker.openbittorrent.com%3A80&amp;tr=udp%3A%2F%2Fopen.demonii.com%3A1337&amp;tr=udp%3A%2F%2Ftracker.coppersurfer.tk%3A6969&amp;tr=udp%3A%2F%2Fexodus.desync.com%3A6969","seeders":1,"leechers":1,"uploader":"sceneline","files":20,"time":1416928213,"description":"-\nFollow us on Facebook  /Speeddotcd\n\nFor the sake of sharing, Please seed as long as you can\n\nEnjoy HD releases \n\n ............ NFO .............\n-\t\nFor more info about this show check NFO file","torrent":{"xt":"urn:btih:69a9695da3e31e8184ee908cde5a91c09e7701d6","amp;dn":"8.Out.Of.10.Cats.S18E08.720p.HDTV.x264-TLA","amp;tr":["udp%3A%2F%2Ftracker.openbittorrent.com%3A80","udp%3A%2F%2Fopen.demonii.com%3A1337","udp%3A%2F%2Ftracker.coppersurfer.tk%3A6969","udp%3A%2F%2Fexodus.desync.com%3A6969"],"infoHash":"69a9695da3e31e8184ee908cde5a91c09e7701d6","infoHashBuffer":{"type":"Buffer","data":[105,169,105,93,163,227,30,129,132,238,144,140,222,90,145,192,158,119,1,214]},"announce":[],"urlList":[]}}