{"title":"Elementary.S01E01.720p.HDTV.X264-DIMENSION [PublicHD]","uid":7680363,"size":966744308,"categoryP":"video","categoryS":"hd___tv_shows","magnet":"?xt=urn:btih:727df8224f94fee628d2bc217743a1f7acba57c0&amp;dn=Elementary.S01E01.720p.HDTV.X264-DIMENSION+%5BPublicHD%5D&amp;tr=udp%3A%2F%2Ftracker.openbittorrent.com%3A80&amp;tr=udp%3A%2F%2Fopen.demonii.com%3A1337&amp;tr=udp%3A%2F%2Ftracker.coppersurfer.tk%3A6969&amp;tr=udp%3A%2F%2Fexodus.desync.com%3A6969","seeders":1,"leechers":0,"uploader":"DibyaTPB","files":2,"time":1348805786,"description":"PublicHD - High-Definition Bittorrent Community \n     &lt;a href=&quot;\nhttp://publichd.eu/&quot; rel=&quot;nofollow&quot; target=&quot;_NEW&quot;&gt;\nhttp://publichd.eu/&lt;/a&gt;\n\n-----------------------------------------------------\n\nElementary.S01E01.720p.HDTV.X264-DIMENSION\nAired 27.09.2012\n\nPilot\n\nDetective Sherlock Holmes, along with his\nsober companion, Dr. Joan Watson, uses his\nuncanny ability to read people and analyze\ncrimes to assist the NYPD on some of their\nmore difficult cases. In the season\npremiere, Holmes consults on a home\ninvasion that resulted in murder\n\n18/Slower\nEvolve... or die","torrent":{"xt":"urn:btih:727df8224f94fee628d2bc217743a1f7acba57c0","amp;dn":"Elementary.S01E01.720p.HDTV.X264-DIMENSION+%5BPublicHD%5D","amp;tr":["udp%3A%2F%2Ftracker.openbittorrent.com%3A80","udp%3A%2F%2Fopen.demonii.com%3A1337","udp%3A%2F%2Ftracker.coppersurfer.tk%3A6969","udp%3A%2F%2Fexodus.desync.com%3A6969"],"infoHash":"727df8224f94fee628d2bc217743a1f7acba57c0","infoHashBuffer":{"type":"Buffer","data":[114,125,248,34,79,148,254,230,40,210,188,33,119,67,161,247,172,186,87,192]},"announce":[],"urlList":[]}}