{"title":"BackroomCastingCouch - Leo - Casting","uid":13097574,"size":762594656,"categoryP":"porn","categoryS":"hd___movies","magnet":"?xt=urn:btih:87d11a8ba958da99f52bde112c2a60c8d0d1f135&amp;dn=BackroomCastingCouch+-+Leo+-+Casting&amp;tr=udp%3A%2F%2Ftracker.leechers-paradise.org%3A6969&amp;tr=udp%3A%2F%2Fzer0day.ch%3A1337&amp;tr=udp%3A%2F%2Fopen.demonii.com%3A1337&amp;tr=udp%3A%2F%2Ftracker.coppersurfer.tk%3A6969&amp;tr=udp%3A%2F%2Fexodus.desync.com%3A6969","seeders":1,"leechers":0,"uploader":"C47wh15p3r3r","files":1,"time":1451161035,"description":"BackroomCastingCouch - Leo - Casting\r\n\r\nScreenshots: \nhttp://imgarte.com/?v=801821 \nhttp://imgarte.com/?v=498710","torrent":{"xt":"urn:btih:87d11a8ba958da99f52bde112c2a60c8d0d1f135","amp;dn":"BackroomCastingCouch+-+Leo+-+Casting","amp;tr":["udp%3A%2F%2Ftracker.leechers-paradise.org%3A6969","udp%3A%2F%2Fzer0day.ch%3A1337","udp%3A%2F%2Fopen.demonii.com%3A1337","udp%3A%2F%2Ftracker.coppersurfer.tk%3A6969","udp%3A%2F%2Fexodus.desync.com%3A6969"],"infoHash":"87d11a8ba958da99f52bde112c2a60c8d0d1f135","infoHashBuffer":{"type":"Buffer","data":[135,209,26,139,169,88,218,153,245,43,222,17,44,42,96,200,208,209,241,53]},"announce":[],"urlList":[]}}