{"title":"The.Crazy.Ones.S01E21.The.Monster.WEB-DL.x264.AAC","uid":9985384,"size":169409636,"categoryP":"video","categoryS":"tv_shows","magnet":"?xt=urn:btih:890a9fef6866651285467c7728338659a5cb47d1&amp;dn=The.Crazy.Ones.S01E21.The.Monster.WEB-DL.x264.AAC&amp;tr=udp%3A%2F%2Ftracker.openbittorrent.com%3A80&amp;tr=udp%3A%2F%2Fopen.demonii.com%3A1337&amp;tr=udp%3A%2F%2Ftracker.coppersurfer.tk%3A6969&amp;tr=udp%3A%2F%2Fexodus.desync.com%3A6969","seeders":1,"leechers":2,"uploader":"loadstone2k12","files":-1,"time":1397785637,"description":"The Crazy Ones - Season 1 - Episode 21 (WEB-DL - MP4)\n-----------------------------------------------------\n\nIn the series' witty and hilarious opening season we meet\nunorthodox Simon (beloved Oscar Winner Robin Williams) and\nhis sensible daughter who's tasked with keeping him in check!\n\nProduced by David E. Kelley Productions and 20th Century Fox Television.\n\n\nSimon's team come up with a radical way to save a library,\nand Gordon serves as the campaign's reluctant poster boy.\n\nThe.Crazy.Ones.S01E21.The.Monster.WEB-DL.x264.AAC.mp4\n\nVideo: MPEG4 Video (H264) 720x404 23.976fps [CRF 19.0]\nAudio: MPEG4 Audio (AAC) 48000Hz stereo  [128Kbps ABR]\nSubs: English Closed Captions (SubRip Text)\nDuration: 00:21:42\nFile size: 161 MB","torrent":{"xt":"urn:btih:890a9fef6866651285467c7728338659a5cb47d1","amp;dn":"The.Crazy.Ones.S01E21.The.Monster.WEB-DL.x264.AAC","amp;tr":["udp%3A%2F%2Ftracker.openbittorrent.com%3A80","udp%3A%2F%2Fopen.demonii.com%3A1337","udp%3A%2F%2Ftracker.coppersurfer.tk%3A6969","udp%3A%2F%2Fexodus.desync.com%3A6969"],"infoHash":"890a9fef6866651285467c7728338659a5cb47d1","infoHashBuffer":{"type":"Buffer","data":[137,10,159,239,104,102,101,18,133,70,124,119,40,51,134,89,165,203,71,209]},"announce":[],"urlList":[]}}