{"title":"In.Your.Hands.2010.DVDRip.XviD-RedBlade","uid":8248681,"size":726611051,"categoryP":"video","categoryS":"movies","magnet":"?xt=urn:btih:aaddbcd0f393bd254904acec00fcb1559dc52e01&amp;dn=In.Your.Hands.2010.DVDRip.XviD-RedBlade&amp;tr=udp%3A%2F%2Ftracker.openbittorrent.com%3A80&amp;tr=udp%3A%2F%2Fopen.demonii.com%3A1337&amp;tr=udp%3A%2F%2Ftracker.coppersurfer.tk%3A6969&amp;tr=udp%3A%2F%2Fexodus.desync.com%3A6969","seeders":1,"leechers":0,"uploader":"Drarbg","files":5,"time":1363115176,"description":"In.Your.Hands.2010.DVDRip.XviD-RedBlade\n-----------------------------------------\nScreens : &lt;a href=&quot;\nhttp://imagecurl.org/viewer.php?file=54115242612742034545.jpg&quot; rel=&quot;nofollow&quot; target=&quot;_NEW&quot;&gt;\nhttp://imagecurl.org/viewer.php?file=54115242612742034545.jpg&lt;/a&gt;\n\n","torrent":{"xt":"urn:btih:aaddbcd0f393bd254904acec00fcb1559dc52e01","amp;dn":"In.Your.Hands.2010.DVDRip.XviD-RedBlade","amp;tr":["udp%3A%2F%2Ftracker.openbittorrent.com%3A80","udp%3A%2F%2Fopen.demonii.com%3A1337","udp%3A%2F%2Ftracker.coppersurfer.tk%3A6969","udp%3A%2F%2Fexodus.desync.com%3A6969"],"infoHash":"aaddbcd0f393bd254904acec00fcb1559dc52e01","infoHashBuffer":{"type":"Buffer","data":[170,221,188,208,243,147,189,37,73,4,172,236,0,252,177,85,157,197,46,1]},"announce":[],"urlList":[]}}