{"title":"TheUpperFloor - Abella Danger And Zoe Parker 11 Mar 2016 mp4","uid":13836650,"size":392950065,"categoryP":"porn","categoryS":"movie_clips","magnet":"?xt=urn:btih:c705fd4d81d436bb432468645fce707309ea0058&amp;dn=TheUpperFloor+-+Abella+Danger+And+Zoe+Parker+11+Mar+2016+mp4&amp;tr=udp%3A%2F%2Ftracker.leechers-paradise.org%3A6969&amp;tr=udp%3A%2F%2Fzer0day.ch%3A1337&amp;tr=udp%3A%2F%2Fopen.demonii.com%3A1337&amp;tr=udp%3A%2F%2Ftracker.coppersurfer.tk%3A6969&amp;tr=udp%3A%2F%2Fexodus.desync.com%3A6969","seeders":1,"leechers":2,"uploader":"ImgSnaps","files":1,"time":1457766084,"description":"Screenshots:\r\n \nhttp://imgsnaps.com/image/yoc\r\n \nhttp://imgsnaps.com/image/yo1\r\n \nhttp://imgsnaps.com/image/yo2","torrent":{"xt":"urn:btih:c705fd4d81d436bb432468645fce707309ea0058","amp;dn":"TheUpperFloor+-+Abella+Danger+And+Zoe+Parker+11+Mar+2016+mp4","amp;tr":["udp%3A%2F%2Ftracker.leechers-paradise.org%3A6969","udp%3A%2F%2Fzer0day.ch%3A1337","udp%3A%2F%2Fopen.demonii.com%3A1337","udp%3A%2F%2Ftracker.coppersurfer.tk%3A6969","udp%3A%2F%2Fexodus.desync.com%3A6969"],"infoHash":"c705fd4d81d436bb432468645fce707309ea0058","infoHashBuffer":{"type":"Buffer","data":[199,5,253,77,129,212,54,187,67,36,104,100,95,206,112,115,9,234,0,88]},"announce":[],"urlList":[]}}