{"title":"Cuenta.Cuentos.18","uid":5457259,"size":54819832,"categoryP":"other","categoryS":"e_books","magnet":"?xt=urn:btih:c7d2202f14828998340fa403210767acc348c4af&amp;dn=Cuenta.Cuentos.18&amp;tr=udp%3A%2F%2Ftracker.openbittorrent.com%3A80&amp;tr=udp%3A%2F%2Fopen.demonii.com%3A1337&amp;tr=udp%3A%2F%2Ftracker.coppersurfer.tk%3A6969&amp;tr=udp%3A%2F%2Fexodus.desync.com%3A6969","seeders":1,"leechers":0,"uploader":"furtaperas","files":1,"time":1269361360,"description":"Cuenta Cuentos 18","torrent":{"xt":"urn:btih:c7d2202f14828998340fa403210767acc348c4af","amp;dn":"Cuenta.Cuentos.18","amp;tr":["udp%3A%2F%2Ftracker.openbittorrent.com%3A80","udp%3A%2F%2Fopen.demonii.com%3A1337","udp%3A%2F%2Ftracker.coppersurfer.tk%3A6969","udp%3A%2F%2Fexodus.desync.com%3A6969"],"infoHash":"c7d2202f14828998340fa403210767acc348c4af","infoHashBuffer":{"type":"Buffer","data":[199,210,32,47,20,130,137,152,52,15,164,3,33,7,103,172,195,72,196,175]},"announce":[],"urlList":[]}}