{"title":"DeepThroatLove.13.07.15.Holly.Michaels.Morning.Arousal.XXX.720p.","uid":8694637,"size":626795194,"categoryP":"porn","categoryS":"other","magnet":"?xt=urn:btih:cb76cf0759556a803c9c66ca112ce4708e199abf&amp;dn=DeepThroatLove.13.07.15.Holly.Michaels.Morning.Arousal.XXX.720p.&amp;tr=udp%3A%2F%2Ftracker.openbittorrent.com%3A80&amp;tr=udp%3A%2F%2Fopen.demonii.com%3A1337&amp;tr=udp%3A%2F%2Ftracker.coppersurfer.tk%3A6969&amp;tr=udp%3A%2F%2Fexodus.desync.com%3A6969","seeders":1,"leechers":0,"uploader":"Drarbg","files":3,"time":1373944563,"description":"DeepThroatLove.13.07.15.Holly.Michaels.Morning.Arousal.XXX.720p.WMV-KTR\n-----------------------------------------\nScreens : &lt;a href=&quot;\nhttp://imagecurl.org/viewer.php?file=56846777398906252362.jpg&quot; rel=&quot;nofollow&quot; target=&quot;_NEW&quot;&gt;\nhttp://imagecurl.org/viewer.php?file=56846777398906252362.jpg&lt;/a&gt;\n\n","torrent":{"xt":"urn:btih:cb76cf0759556a803c9c66ca112ce4708e199abf","amp;dn":"DeepThroatLove.13.07.15.Holly.Michaels.Morning.Arousal.XXX.720p.","amp;tr":["udp%3A%2F%2Ftracker.openbittorrent.com%3A80","udp%3A%2F%2Fopen.demonii.com%3A1337","udp%3A%2F%2Ftracker.coppersurfer.tk%3A6969","udp%3A%2F%2Fexodus.desync.com%3A6969"],"infoHash":"cb76cf0759556a803c9c66ca112ce4708e199abf","infoHashBuffer":{"type":"Buffer","data":[203,118,207,7,89,85,106,128,60,156,102,202,17,44,228,112,142,25,154,191]},"announce":[],"urlList":[]}}