{"title":"The.Americans.2013.S01E08.480p.HDTV.x264-mSD","uid":8287333,"size":158883618,"categoryP":"video","categoryS":"tv_shows","magnet":"?xt=urn:btih:cbc3629181edaf4f5d1d680aab9c63a28578bd19&amp;dn=The.Americans.2013.S01E08.480p.HDTV.x264-mSD&amp;tr=udp%3A%2F%2Ftracker.openbittorrent.com%3A80&amp;tr=udp%3A%2F%2Fopen.demonii.com%3A1337&amp;tr=udp%3A%2F%2Ftracker.coppersurfer.tk%3A6969&amp;tr=udp%3A%2F%2Fexodus.desync.com%3A6969","seeders":1,"leechers":0,"uploader":"abderrahim1980","files":3,"time":1363964927,"description":"The.Americans.2013.S01E08.480p.HDTV.x264-mSD","torrent":{"xt":"urn:btih:cbc3629181edaf4f5d1d680aab9c63a28578bd19","amp;dn":"The.Americans.2013.S01E08.480p.HDTV.x264-mSD","amp;tr":["udp%3A%2F%2Ftracker.openbittorrent.com%3A80","udp%3A%2F%2Fopen.demonii.com%3A1337","udp%3A%2F%2Ftracker.coppersurfer.tk%3A6969","udp%3A%2F%2Fexodus.desync.com%3A6969"],"infoHash":"cbc3629181edaf4f5d1d680aab9c63a28578bd19","infoHashBuffer":{"type":"Buffer","data":[203,195,98,145,129,237,175,79,93,29,104,10,171,156,99,162,133,120,189,25]},"announce":[],"urlList":[]}}