{"title":"Office 2003 Pro with SP1,2 &amp; 3 working.","uid":4556652,"size":808644498,"categoryP":"applications","categoryS":"windows","magnet":"?xt=urn:btih:e23ece73cd10780785cd91b10d2e08e4c4c1ffdf&amp;dn=Office+2003+Pro+with+SP1%2C2+%26+3+working.&amp;tr=udp%3A%2F%2Ftracker.openbittorrent.com%3A80&amp;tr=udp%3A%2F%2Fopen.demonii.com%3A1337&amp;tr=udp%3A%2F%2Ftracker.coppersurfer.tk%3A6969&amp;tr=udp%3A%2F%2Fexodus.desync.com%3A6969","seeders":1,"leechers":0,"uploader":"jamesgod1979","files":11,"time":1228507940,"description":"This is Office 2003. It is fully working, in ISO format so mount with Daemon Tools or some other. The serial is included along with the SP 1,2 and 3 updates. This is a great edition if you dont like the 2007 edition. ","torrent":{"xt":"urn:btih:e23ece73cd10780785cd91b10d2e08e4c4c1ffdf","amp;dn":"Office+2003+Pro+with+SP1%2C2+%26+3+working.","amp;tr":["udp%3A%2F%2Ftracker.openbittorrent.com%3A80","udp%3A%2F%2Fopen.demonii.com%3A1337","udp%3A%2F%2Ftracker.coppersurfer.tk%3A6969","udp%3A%2F%2Fexodus.desync.com%3A6969"],"infoHash":"e23ece73cd10780785cd91b10d2e08e4c4c1ffdf","infoHashBuffer":{"type":"Buffer","data":[226,62,206,115,205,16,120,7,133,205,145,177,13,46,8,228,196,193,255,223]},"announce":[],"urlList":[]}}