{"title":"300 Optical Illusions.","uid":5289315,"size":36736906,"categoryP":"other","categoryS":"pictures","magnet":"?xt=urn:btih:f1301f77c6f0b0e924f4df4a5076daeb1fbedc74&amp;dn=300+Optical+Illusions.&amp;tr=udp%3A%2F%2Ftracker.openbittorrent.com%3A80&amp;tr=udp%3A%2F%2Fopen.demonii.com%3A1337&amp;tr=udp%3A%2F%2Ftracker.coppersurfer.tk%3A6969&amp;tr=udp%3A%2F%2Fexodus.desync.com%3A6969","seeders":1,"leechers":1,"uploader":"thenoobish","files":1,"time":1263842372,"description":"300 Optical Illusions. :)","torrent":{"xt":"urn:btih:f1301f77c6f0b0e924f4df4a5076daeb1fbedc74","amp;dn":"300+Optical+Illusions.","amp;tr":["udp%3A%2F%2Ftracker.openbittorrent.com%3A80","udp%3A%2F%2Fopen.demonii.com%3A1337","udp%3A%2F%2Ftracker.coppersurfer.tk%3A6969","udp%3A%2F%2Fexodus.desync.com%3A6969"],"infoHash":"f1301f77c6f0b0e924f4df4a5076daeb1fbedc74","infoHashBuffer":{"type":"Buffer","data":[241,48,31,119,198,240,176,233,36,244,223,74,80,118,218,235,31,190,220,116]},"announce":[],"urlList":[]}}