{"title":"Canopy 2013 DVDRip x264-RedBlade","uid":11303529,"size":632451175,"categoryP":"video","categoryS":"movies","magnet":"?xt=urn:btih:f540e49072150962410c70ac456da8ee41ff40d6&amp;dn=Canopy+2013+DVDRip+x264-RedBlade&amp;tr=udp%3A%2F%2Ftracker.openbittorrent.com%3A80&amp;tr=udp%3A%2F%2Fopen.demonii.com%3A1337&amp;tr=udp%3A%2F%2Ftracker.coppersurfer.tk%3A6969&amp;tr=udp%3A%2F%2Fexodus.desync.com%3A6969","seeders":1,"leechers":0,"uploader":"hotpena","files":5,"time":1414448298,"description":"\nCOVER: &lt;a href=&quot;\nhttp://www.imgili.com/viewer.php?file=95311332643692656157.jpg&quot; rel=&quot;nofollow&quot; target=&quot;_NEW&quot;&gt;\nhttp://www.imgili.com/viewer.php?file=95311332643692656157.jpg&lt;/a&gt;\n\nPLOT: \nWartime, 1942. Singapore. An Australian fighter pilot shot down in combat awakens suspended in the treetops. As night devours day, he must navigate through dangerous jungle in search of sanctuary. Transcending language and culture, CANOPY is a cinematic tour de force exploring the collision of war, nature and its impact on humanity.              \n\nACTORS: \nKhan Chittenden, Tzu-yi 'Morning' Mo, Robert Menzies, Edwina Wren, \n\nRELEASED: \n 29 August 2014 \n\nIMDB: &lt;a href=&quot;\nhttp://www.imdb.com/title/tt2232578/&quot; rel=&quot;nofollow&quot; target=&quot;_NEW&quot;&gt;\nhttp://www.imdb.com/title/tt2232578/&lt;/a&gt;\n\n\n\n Size: 632069044 bytes (602.79 MiB), duration: 01:22:53, avg.bitrate: 1017 kb/s\nAudio: aac, 48000 Hz, stereo (eng)\nVideo: h264, yuv420p, 704x358, 23.98 fps(r) (eng)\n &lt;a href=&quot;\nhttp://www.imgili.com/viewer.php?file=70141804308580726235.jpg&quot; rel=&quot;nofollow&quot; target=&quot;_NEW&quot;&gt;\nhttp://www.imgili.com/viewer.php?file=70141804308580726235.jpg&lt;/a&gt;\n &lt;a href=&quot;\nhttp://www.imgili.com/viewer.php?file=48648645583157541043.jpg&quot; rel=&quot;nofollow&quot; target=&quot;_NEW&quot;&gt;\nhttp://www.imgili.com/viewer.php?file=48648645583157541043.jpg&lt;/a&gt;\n  &lt;a href=&quot;\nhttp://www.imgili.com/viewer.php?file=96923064374099482178.jpg&quot; rel=&quot;nofollow&quot; target=&quot;_NEW&quot;&gt;\nhttp://www.imgili.com/viewer.php?file=96923064374099482178.jpg&lt;/a&gt;\n \n\n\nDOWNLOAD AND ENJOY. \n\n KEEP IT FOR LONG SEEDING TO HELP OTHERS \n\n \n Thanks to : RedBlade\n Movie Share","torrent":{"xt":"urn:btih:f540e49072150962410c70ac456da8ee41ff40d6","amp;dn":"Canopy+2013+DVDRip+x264-RedBlade","amp;tr":["udp%3A%2F%2Ftracker.openbittorrent.com%3A80","udp%3A%2F%2Fopen.demonii.com%3A1337","udp%3A%2F%2Ftracker.coppersurfer.tk%3A6969","udp%3A%2F%2Fexodus.desync.com%3A6969"],"infoHash":"f540e49072150962410c70ac456da8ee41ff40d6","infoHashBuffer":{"type":"Buffer","data":[245,64,228,144,114,21,9,98,65,12,112,172,69,109,168,238,65,255,64,214]},"announce":[],"urlList":[]}}