{"title":"Sensual Jane Dirty Secretary","uid":15822439,"size":90172043,"categoryP":"porn","categoryS":"movie_clips","magnet":"?xt=urn:btih:fe4e1c258ad59091a158931405db2b909d24343b&amp;dn=Sensual+Jane+Dirty+Secretary&amp;tr=udp%3A%2F%2Ftracker.leechers-paradise.org%3A6969&amp;tr=udp%3A%2F%2Fzer0day.ch%3A1337&amp;tr=udp%3A%2F%2Fopen.demonii.com%3A1337&amp;tr=udp%3A%2F%2Ftracker.coppersurfer.tk%3A6969&amp;tr=udp%3A%2F%2Fexodus.desync.com%3A6969","seeders":1,"leechers":0,"uploader":"demonoidt","files":1,"time":1473788756,"description":"Samples\r\n \nhttp://torrentzz.co/sensual-jane-dirty-secretary/\r\n \nhttp://torrentzz.co/sensual-jane-dirty-secretary-2/","torrent":{"xt":"urn:btih:fe4e1c258ad59091a158931405db2b909d24343b","amp;dn":"Sensual+Jane+Dirty+Secretary","amp;tr":["udp%3A%2F%2Ftracker.leechers-paradise.org%3A6969","udp%3A%2F%2Fzer0day.ch%3A1337","udp%3A%2F%2Fopen.demonii.com%3A1337","udp%3A%2F%2Ftracker.coppersurfer.tk%3A6969","udp%3A%2F%2Fexodus.desync.com%3A6969"],"infoHash":"fe4e1c258ad59091a158931405db2b909d24343b","infoHashBuffer":{"type":"Buffer","data":[254,78,28,37,138,213,144,145,161,88,147,20,5,219,43,144,157,36,52,59]},"announce":[],"urlList":[]}}